MANIFEST.in
README.txt
setup.cfg
setup.py
docs/HISTORY.txt
horae/__init__.py
horae.cache.egg-info/PKG-INFO
horae.cache.egg-info/SOURCES.txt
horae.cache.egg-info/dependency_links.txt
horae.cache.egg-info/entry_points.txt
horae.cache.egg-info/namespace_packages.txt
horae.cache.egg-info/not-zip-safe
horae.cache.egg-info/requires.txt
horae.cache.egg-info/top_level.txt
horae/cache/__init__.py
horae/cache/cache.py
horae/cache/configure.zcml
horae/cache/interfaces.py
horae/cache/request.py
horae/cache/vocabulary.py