Metadata-Version: 1.0
Name: horae.cache
Version: 1.0a1
Summary: Provides utilities and decorators for caching
Home-page: UNKNOWN
Author: Simon Kaeser
Author-email: skaeser@gmail.com
License: GPL
Platform: UNKNOWN
Classifier: Programming Language :: Python
